dosertools/__init__.py
dosertools/data_processing/__init__.py
dosertools/data_processing/array.py
dosertools/data_processing/csv.py
dosertools/data_processing/extension.py
dosertools/data_processing/figures.py
dosertools/data_processing/fitting.py
dosertools/data_processing/integration.py
dosertools/file_handling/__init__.py
dosertools/file_handling/folder.py
dosertools/file_handling/tags.py
dosertools/image_processing/__init__.py
dosertools/image_processing/binary.py
dosertools/image_processing/tiff_handling.py
dosertools-1.0.2.dist-info/LICENSE
dosertools-1.0.2.dist-info/METADATA
dosertools-1.0.2.dist-info/WHEEL
dosertools-1.0.2.dist-info/top_level.txt
dosertools-1.0.2.dist-info/RECORD
