Metadata-Version: 2.1
Name: dosertools
Version: 1.0.2
Summary: dosertools is a Python package for analyzing dripping-onto-substrate extensional rheology (DoSER) videos.
Home-page: https://github.com/rlearsch/dosertools
Author: Rob Learsch and Red Lhota
Author-email: rlearsch@caltech.edu
License: UNKNOWN
Project-URL: Bug Tracker, https://github.com/rlearsch/dosertools/issues
Platform: UNKNOWN
Classifier: Programming Language :: Python :: 3
Classifier: License :: OSI Approved :: MIT License
Classifier: Operating System :: OS Independent
Requires-Python: >=3.8
License-File: LICENSE
Requires-Dist: pytest
Requires-Dist: numpy
Requires-Dist: scikit-image
Requires-Dist: pandas
Requires-Dist: imagecodecs
Requires-Dist: sphinx
Requires-Dist: holoviews
